LICENSE
README.md
knightvision/__init__.py
knightvision/assets.py
knightvision/cli.py
knightvision/game.py
knightvision/io.py
knightvision/models.py
knightvision/pipeline.py
knightvision/processing.py
knightvision-0.1.0.dist-info/METADATA
knightvision-0.1.0.dist-info/WHEEL
knightvision-0.1.0.dist-info/entry_points.txt
knightvision-0.1.0.dist-info/licenses/LICENSE
knightvision-0.1.0.dist-info/RECORD
