Metadata-Version: 2.4
Name: knightvision
Version: 0.1.0
Summary: CLI + library to convert chess video to PGN
Project-URL: Homepage, https://github.com/nickbuice/knightvision
Author-email: "Nicholas W. Buice" <nw.buice@gmail.com>
License: 
License-File: LICENSE
Classifier: License :: OSI Approved :: Apache Software License
Classifier: Operating System :: OS Independent
Classifier: Programming Language :: Python :: 3
Classifier: Topic :: Games/Entertainment :: Board Games
Requires-Python: >=3.10
Requires-Dist: chess>=1.11.2
Requires-Dist: numpy<2.3.0,>=2
Requires-Dist: onnxruntime>=1.18
Requires-Dist: opencv-python>=4.10
Requires-Dist: typer>=0.9
